licenseware/__init__.py
licenseware/app_builder/__init__.py
licenseware/app_builder/app_activation_route.py
licenseware/app_builder/app_builder.py
licenseware/app_builder/app_registration_route.py
licenseware/app_builder/download_as_route.py
licenseware/app_builder/editable_tables_route.py
licenseware/app_builder/features_route.py
licenseware/app_builder/refresh_registration_route.py
licenseware/app_builder/reprocess_data_route.py
licenseware/app_builder/tenant_registration_route.py
licenseware/app_builder/terms_and_conditions_route.py
licenseware/app_builder/data_sync_namespace/__init__.py
licenseware/app_builder/data_sync_namespace/data_sync_namespace.py
licenseware/app_builder/decrypt_namespace/__init__.py
licenseware/app_builder/decrypt_namespace/decrypt_namespace.py
licenseware/app_builder/endpoint_builder_namespace/__init__.py
licenseware/app_builder/features_namespace/__init__.py
licenseware/app_builder/features_namespace/features_namespace.py
licenseware/app_builder/report_components_namespace/__init__.py
licenseware/app_builder/report_components_namespace/report_individual_components_namespace.py
licenseware/app_builder/reports_namespace/__init__.py
licenseware/app_builder/reports_namespace/report_components_namespace.py
licenseware/app_builder/reports_namespace/report_image_preview_dark_namespace.py
licenseware/app_builder/reports_namespace/report_image_preview_namespace.py
licenseware/app_builder/reports_namespace/report_metadata_namespace.py
licenseware/app_builder/reports_namespace/report_public_components_namespace.py
licenseware/app_builder/reports_namespace/report_public_metadata_namespace.py
licenseware/app_builder/reports_namespace/report_register_namespace.py
licenseware/app_builder/reports_namespace/report_snapshot_namespace.py
licenseware/app_builder/uploads_namespace/__init__.py
licenseware/app_builder/uploads_namespace/filenames_validation_namespace.py
licenseware/app_builder/uploads_namespace/filestream_validation_namespace.py
licenseware-2.4.7.dist-info/LICENSE
licenseware-2.4.7.dist-info/METADATA
licenseware-2.4.7.dist-info/WHEEL
licenseware-2.4.7.dist-info/entry_points.txt
licenseware-2.4.7.dist-info/top_level.txt
licenseware-2.4.7.dist-info/RECORD
