Metadata-Version: 2.1
Name: licenseware
Version: 2.4.7
Summary: Common utilities for licenseware.
Home-page: https://licenseware.io/
Author: Licenseware
Author-email: contact@licenseware.io
License: Apache License 2.0
Platform: UNKNOWN
Classifier: Development Status :: 5 - Production/Stable
Classifier: Framework :: Flask
Classifier: Programming Language :: Python
Classifier: Programming Language :: Python :: 3
Classifier: Programming Language :: Python :: 3.8
Classifier: License :: OSI Approved :: Apache Software License
Classifier: Operating System :: OS Independent
Classifier: Topic :: Internet :: WWW/HTTP :: Dynamic Content
Classifier: Topic :: Internet :: WWW/HTTP :: HTTP Servers
Classifier: Topic :: Internet :: WWW/HTTP :: WSGI
Classifier: Topic :: Internet :: WWW/HTTP :: WSGI :: Application
Classifier: Topic :: Software Development :: Libraries :: Python Modules
Requires-Python: ==3.8.*
Requires-Dist: Babel (==2.9.1)
Requires-Dist: cachetools (==5.0.0)
Requires-Dist: dnspython (==2.2.1)
Requires-Dist: dramatiq (==1.11.0)
Requires-Dist: Flask (==2.0.3)
Requires-Dist: Flask-Cors (==3.0.10)
Requires-Dist: flask-restx (==0.5.1)
Requires-Dist: loguru (==0.6.0)
Requires-Dist: marshmallow (==3.18.0)
Requires-Dist: marshmallow-jsonschema (==0.11.1)
Requires-Dist: openpyxl (==3.0.7)
Requires-Dist: pandas (==1.2.4)
Requires-Dist: pdoc3 (==0.10.0)
Requires-Dist: pycryptodome (==3.14.1)
Requires-Dist: PyJWT (==2.4.0)
Requires-Dist: pymongo (==3.12.0)
Requires-Dist: python-dotenv (==0.19.0)
Requires-Dist: redis (==3.5.3)
Requires-Dist: requests (==2.28.1)
Requires-Dist: sendgrid (==6.9.1)
Requires-Dist: typer (==0.4.1)
Requires-Dist: uWSGI (==2.0.19.1)
Requires-Dist: werkzeug (==2.0.3)
Provides-Extra: all
Requires-Dist: trend-app-protect (==4.6.2) ; extra == 'all'
Requires-Dist: opentelemetry-instrumentation (==0.26b1) ; extra == 'all'
Requires-Dist: opentelemetry-exporter-otlp (==1.7.1) ; extra == 'all'
Requires-Dist: opentelemetry-distro (==0.26b1) ; extra == 'all'
Requires-Dist: dramatiq[watch] ; extra == 'all'
Requires-Dist: prometheus-flask-exporter (~=0.20.3) ; extra == 'all'
Requires-Dist: honcho (==1.0.1) ; extra == 'all'
Requires-Dist: confluent-kafka (==1.9.0) ; extra == 'all'
Provides-Extra: honcho
Requires-Dist: honcho (==1.0.1) ; extra == 'honcho'
Provides-Extra: kafka
Requires-Dist: confluent-kafka (==1.9.0) ; extra == 'kafka'
Provides-Extra: opentelemetry
Requires-Dist: opentelemetry-distro (==0.26b1) ; extra == 'opentelemetry'
Requires-Dist: opentelemetry-instrumentation (==0.26b1) ; extra == 'opentelemetry'
Requires-Dist: opentelemetry-exporter-otlp (==1.7.1) ; extra == 'opentelemetry'
Provides-Extra: prometheus
Requires-Dist: prometheus-flask-exporter (~=0.20.3) ; extra == 'prometheus'
Provides-Extra: trend-app
Requires-Dist: trend-app-protect (==4.6.2) ; extra == 'trend-app'
Provides-Extra: watchdog
Requires-Dist: dramatiq[watch] ; extra == 'watchdog'
